ModelMarketSDK/ForumAIModelMarket.json
ModelMarketSDK/ForumAIModelMarketSKALE.json
ModelMarketSDK/Mixtral8x7BMarket.json
ModelMarketSDK/ModelMarket.py
ModelMarketSDK/USDC.json
ModelMarketSDK/__init__.py
forumaisdk-0.0.6.dist-info/LICENSE
forumaisdk-0.0.6.dist-info/METADATA
forumaisdk-0.0.6.dist-info/WHEEL
forumaisdk-0.0.6.dist-info/top_level.txt
forumaisdk-0.0.6.dist-info/RECORD
